[
    {"id":"1","title":"예약신청문의드려요","write":"s2s2@naver.com","content":"2025년 12월31일 날 예약가능한가요?","date":"2023.08.30",
    "to":"0","answer":":"},
    {"id":"2","title":"주차장안내","write":"tlqkf18@daum.net","content":"23년12월3일에 예약한 사람인데요, 주차장 안내를 못받았어요","date":"2023.08.29",
    "to":"1","answer":"안녕하세요,010-2345-8880으로 문자남겨주시면 친절하게 답해드려요"},
    {"id":"3","title":"스튜디오금액","write":"spoty77@daum.net","content":"스튜디오 금액을 알고 싶어요","date":"2023.07.07",
    "to":"1","answer":"기본촬영 2인 80만원, 인원 추가시 10만원의 비용이 발생합니다. 자세한 사항은 나다운스튜디오 홈페이지를 참고해주세요"},
    {"id":"4","title":"에스파 카리나랑 결혼하는 방법","write":"sam34@naver.com","content":"카리나랑 결혼하고싶어요 방법이 없을까요?","date":"2021.04.01",
    "to":"0","answer":":"},
    {"id":"5","title":"드레스대여문의","write":"meinll@naver.com","content":"스튜디오랑 메이크업은 예약했는데, 혹시 드레스도 대여해주시나요?","date":"2021.03.10",
    "to":"1","answer":"드레스 대여는 제휴업체를 통해 진행하고 있습니다. 제휴업체번호를 남겨드릴테니 문의해주세요 010-7895-1126"}
]